Metadata-Version: 2.1
Name: lyser
Version: 1.3
